Metadata-Version: 2.1
Name: odoo9-addon-partner-contact-gender
Version: 9.0.1.1.0.99.dev36
Summary: Add gender field to contacts
Home-page: https://odoo-community.org/
Author: Grupo ESOC, Odoo Community Association (OCA)
Author-email: support@odoo-community.org
License: AGPL-3
Platform: UNKNOWN
Classifier: Programming Language :: Python
Classifier: Framework :: Odoo
Classifier: Framework :: Odoo :: 9.0
Classifier: License :: OSI Approved :: GNU Affero General Public License v3
Requires-Python: ~=2.7
Requires-Dist: odoo9-addon-partner-contact-personal-information-page
Requires-Dist: odoo (<9.1a,>=9.0a)
